azcam_focus/__init__.py
azcam_focus/focus.py
azcam_focus-22.3.2.dist-info/LICENSE
azcam_focus-22.3.2.dist-info/WHEEL
azcam_focus-22.3.2.dist-info/METADATA
azcam_focus-22.3.2.dist-info/RECORD
