Metadata-Version: 2.1
Name: azcam-focus
Version: 22.3.2
Summary: Azcam extension to control focus observations used to determine optimal instrument or telescope focus positions
Keywords: ccd,imaging,astronomy,sensors
Author: Michael Lesser
Author-email: mlesser@arizona.edu
Requires-Dist: azcam
Project-URL: Documentation, https://mplesser.github.io/azcam/
Project-URL: Repository, https://github.com/mplesser/azcam-focus/
